hnt_sap_gui/RPA_HNT_Constants.py
hnt_sap_gui/__init__.py
hnt_sap_gui/hnt_sap.py
hnt_sap_gui/hnt_sap_exception.py
hnt_sap_gui/common/sap_status_bar.py
hnt_sap_gui/common/session.py
hnt_sap_gui/common/tx_result.py
hnt_sap_gui/nota_fiscal/fatura_transaction.py
hnt_sap_gui/nota_fiscal/liberacao_transaction.py
hnt_sap_gui/nota_fiscal/me21n_query_transaction.py
hnt_sap_gui/nota_fiscal/miro_transaction.py
hnt_sap_gui/nota_fiscal/nota_pedido_transaction.py
hnt_sap_service_library-0.0.36.dist-info/METADATA
hnt_sap_service_library-0.0.36.dist-info/WHEEL
hnt_sap_service_library-0.0.36.dist-info/top_level.txt
hnt_sap_service_library-0.0.36.dist-info/RECORD
