Metadata-Version: 2.1
Name: hnt_sap_service_library
Version: 0.0.36
Summary: Lib to access sap gui to run service transactions.
Author: Pepe
Maintainer: Guillerme
License: MIT License
Keywords: nota_fiscal
Requires-Dist: python-dotenv
Requires-Dist: robotframework-sapguilibrary
